pi5neo/__init__.py
pi5neo/pi5neo.py
pi5neo-1.0.5.dist-info/licenses/LICENSE
pi5neo-1.0.5.dist-info/METADATA
pi5neo-1.0.5.dist-info/WHEEL
pi5neo-1.0.5.dist-info/top_level.txt
pi5neo-1.0.5.dist-info/RECORD
