Metadata-Version: 2.4
Name: Pi5Neo
Version: 1.0.5
Summary: A NeoPixel LED control library for Raspberry Pi 5 using SPI
Home-page: https://github.com/vanshksingh/pi5neo
Author: Vansh Kumar Singh
Author-email: vsvsasas@gmail.com
Keywords: raspberrypi5,neopixel,spi,led-strip,hardware
Platform: Raspberry Pi 5
Platform: Equivalent Raspberry Pi boards
Classifier: Programming Language :: Python :: 3
Classifier: License :: OSI Approved :: MIT License
Classifier: Operating System :: POSIX :: Linux
Classifier: Topic :: System :: Hardware :: Hardware Drivers
Classifier: Topic :: Software Development :: Libraries :: Python Modules
Requires-Python: >=3.6
License-File: LICENSE
Requires-Dist: spidev
Dynamic: author
Dynamic: author-email
Dynamic: classifier
Dynamic: description
Dynamic: description-content-type
Dynamic: home-page
Dynamic: keywords
Dynamic: license-file
Dynamic: platform
Dynamic: requires-dist
Dynamic: requires-python
Dynamic: summary
